list_files_with_timestats/LICENSE
list_files_with_timestats/README.MD
list_files_with_timestats/__init__.py
list_files_with_timestats/requirements.txt
list_files_with_timestats/thirdparty.json
list_files_with_timestats-0.11.dist-info/LICENSE.rst
list_files_with_timestats-0.11.dist-info/METADATA
list_files_with_timestats-0.11.dist-info/WHEEL
list_files_with_timestats-0.11.dist-info/top_level.txt
list_files_with_timestats-0.11.dist-info/RECORD
